setup.py
foundry/__init__.py
foundry.egg-info/PKG-INFO
foundry.egg-info/SOURCES.txt
foundry.egg-info/dependency_links.txt
foundry.egg-info/not-zip-safe
foundry.egg-info/requires.txt
foundry.egg-info/top_level.txt