Metadata-Version: 1.1
Name: foundry
Version: 0.0.3
Summary: Casting objects from seed data.
Home-page: http://github.com/eriktaubeneck/foundry
Author: Erik Taubeneck
Author-email: erik.taubeneck@gmail.com
License: MIT
Platform: any
Classifier: Development Status :: 3 - Alpha
Classifier: Environment :: Plugins
Classifier: Intended Audience :: Developers
Classifier: License :: OSI Approved :: MIT License
Classifier: Natural Language :: English 
Classifier: Operating System :: OS Independent
Classifier: Programming Language :: Python
Classifier: Topic :: Software Development :: Build Tools
Classifier: Topic :: Software Development :: Libraries :: Python Modules
